CHANGES.txt
LICENSE.txt
MANIFEST.in
README.txt
setup.py
docs/DESIGN.txt
docs/GeneralUML.graffle
docs/INSTALL.txt
docs/SPECS.txt
docs/TODO.txt
docs/UNINSTALL.txt
docs/VOCABULARY.txt
docs/Wall.bmml
docs/devel.txt
numericube_twistranet.egg-info/PKG-INFO
numericube_twistranet.egg-info/SOURCES.txt
numericube_twistranet.egg-info/dependency_links.txt
numericube_twistranet.egg-info/entry_points.txt
numericube_twistranet.egg-info/not-zip-safe
numericube_twistranet.egg-info/requires.txt
numericube_twistranet.egg-info/top_level.txt
twistranet/__init__.py
twistranet/translation.py
twistranet/actions/__init__.py
twistranet/actions/models.py
twistranet/content_types/__init__.py
twistranet/content_types/forms.py
twistranet/content_types/models.py
twistranet/core/__init__.py
twistranet/core/bootstrap.py
twistranet/core/caches.py
twistranet/core/install.py
twistranet/core/middleware.py
twistranet/core/test_runner.py
twistranet/core/twistranet_project.py
twistranet/core/views.py
twistranet/core/locale/fr/LC_MESSAGES/django.mo
twistranet/core/locale/fr/LC_MESSAGES/django.po
twistranet/core/patches/__init__.py
twistranet/core/patches/django_contrib_auth.py
twistranet/core/patches/sort_thumbnail.py
twistranet/fixtures/__init__.py
twistranet/fixtures/bootstrap.py
twistranet/fixtures/heavy_load.py
twistranet/fixtures/help_en.py
twistranet/fixtures/sample.py
twistranet/fixtures/resources/address_64.png
twistranet/fixtures/resources/application_msword.png
twistranet/fixtures/resources/application_pdf.png
twistranet/fixtures/resources/application_vnd.ms-excel.png
twistranet/fixtures/resources/application_vnd.ms-powerpoint.png
twistranet/fixtures/resources/application_x-shockwave-flash.png
twistranet/fixtures/resources/application_zip.png
twistranet/fixtures/resources/bubble_64.png
twistranet/fixtures/resources/default_a_picture.png
twistranet/fixtures/resources/default_account_picture.png
twistranet/fixtures/resources/default_admin_picture.png
twistranet/fixtures/resources/default_b_picture.png
twistranet/fixtures/resources/default_c_picture.png
twistranet/fixtures/resources/default_community_picture.png
twistranet/fixtures/resources/default_document_picture.png
twistranet/fixtures/resources/default_menu_picture.png
twistranet/fixtures/resources/default_resource_picture.png
