Metadata-Version: 1.0
Name: numericube-twistranet
Version: 2.0.0
Summary: twistranet - An Enterprise Social Network
Home-page: http://numericube.com
Author: numeriCube
Author-email: twistranet@numericube.com
License: GNU Affero General Public License v3
Keywords: twistranet Enterprise Social Network
Platform: UNKNOWN
Classifier: Environment :: Web Environment
Classifier: Framework :: Django
Classifier: Intended Audience :: Information Technology
Classifier: Operating System :: OS Independent
Classifier: Programming Language :: Python :: 2
Classifier: Development Status :: 5 - Production/Stable
Classifier: Topic :: Internet :: WWW/HTTP
Classifier: Topic :: Internet :: WWW/HTTP :: Dynamic Content
Classifier: Topic :: Internet :: WWW/HTTP :: WSGI
Classifier: Topic :: Software Development :: Libraries :: Application Frameworks
Classifier: Topic :: Software Development :: Libraries :: Python Modules
Classifier: License :: OSI Approved :: GNU Affero General Public License v3
